deformers/__init__.py
deformers/models/__init__.py
deformers/models/openai/__init__.py
deformers/models/openai/gptoss.py
deformers-0.0.4.dist-info/METADATA
deformers-0.0.4.dist-info/WHEEL
deformers-0.0.4.dist-info/RECORD
