Metadata-Version: 2.3
Name: deformers
Version: 0.0.4
Summary: Reverse engineer transformer models.
License: .github/LICENSE.md
Author: apehex
Author-email: apehex@protonmail.com
Requires-Python: >=3.10,<3.14
Classifier: License :: Other/Proprietary License
Classifier: Programming Language :: Python :: 3
Classifier: Programming Language :: Python :: 3.10
Classifier: Programming Language :: Python :: 3.11
Classifier: Programming Language :: Python :: 3.12
Classifier: Programming Language :: Python :: 3.13
Requires-Dist: mlable-torch (>=0.2.8)
Requires-Dist: transformers (>=4.0)
